mongoapi/__init__.py
mongoapi-1.0.2.dist-info/LICENSE
mongoapi-1.0.2.dist-info/METADATA
mongoapi-1.0.2.dist-info/WHEEL
mongoapi-1.0.2.dist-info/top_level.txt
mongoapi-1.0.2.dist-info/RECORD
